LICENSE
README.md
setup.py
ul_lib/__init__.py
ul_lib/algorithm_analysis.py
ul_lib/clustering.py
ul_lib/geometry.py
ul_lib.egg-info/PKG-INFO
ul_lib.egg-info/SOURCES.txt
ul_lib.egg-info/dependency_links.txt
ul_lib.egg-info/requires.txt
ul_lib.egg-info/top_level.txt