Metadata-Version: 2.1
Name: ul-lib
Version: 0.0.1a1
Summary: A library for easy use of unsupervised learning algorithms.
Home-page: https://gitlab.com/dmatryus.sqrt49/ul_lib
Author: Dmatryus Detry
Author-email: dmatryus.sqrt49@yandex.ru
License: MIT
Keywords: UL,unsupervised learning,ML,machine learning,optimization
License-File: LICENSE
